.gitignore
MANIFEST.in
README.md
README.txt
setup.py
docs/HISTORY.txt
raptus/__init__.py
raptus.article.filtertable.egg-info/PKG-INFO
raptus.article.filtertable.egg-info/SOURCES.txt
raptus.article.filtertable.egg-info/dependency_links.txt
raptus.article.filtertable.egg-info/entry_points.txt
raptus.article.filtertable.egg-info/namespace_packages.txt
raptus.article.filtertable.egg-info/not-zip-safe
raptus.article.filtertable.egg-info/requires.txt
raptus.article.filtertable.egg-info/top_level.txt
raptus/article/__init__.py
raptus/article/filtertable/__init__.py