Metadata-Version: 1.0
Name: raptus.article.filtertable
Version: 0.3
Summary: 'Provides a filterable table that list all aritcles.
Home-page: http://svn.plone.org/svn/collective/
Author: UNKNOWN
Author-email: UNKNOWN
License: GPL
Platform: UNKNOWN
Classifier: Programming Language :: Python
